[
    {
        "New Price": "20400000",
        "picture": "https://i.ibb.co/Qpn5fFR/toyota-fortuner.jpg",
        "name": "Suzuki Fortuner",
        "company": "Suzuki",
        "location": "Chittagong",
        "Resale Price": "15000000",
        "Years": "5 Years",
        "Seller":"Robin Hossain",
        "post": "November 5, 2022",
        "categoryName":"Suzuki"
    },
    {
        "New Price": "1770000",
        "picture": "https://i.ibb.co/YDWcZcY/Toyota-Camry.jpg",
        "name": "Suzuki Camre",
        "company": "Suzuki",
        "location": "Savar Dhaka",
        "Resale Price": "1220000",
        "Years": "6 years",
        "Seller":"Rokib Hossain",
        "post": "October 12, 2022",
        "categoryName":"Suzuki"
    },
    {
        "New Price": "15243000",
        "picture": "https://i.ibb.co/CVgW89x/toyota.jpg",
        "name": "Suzuki Special",
        "company": "Suzuki",
        "location": "Dhanmondi, Dhaka",
        "Resale Price": "10243000",
        "Years": "2 Years",
        "Seller":"Rahul Hossain",
        "post": "October 10, 2022",
        "categoryName":"Suzuki"
    },
    {
        "New Price": "2546000",
        "picture": "https://i.ibb.co/Qr3f8mL/Toyota-vans.jpg",
        "name": "Suzuki Vans",
        "company": "Suzuki",
        "location": "Bonani Dhaka",
        "Resale Price": "2046000",
        "Years": "6 years",
        "Seller":"Robiul Hossain",
        "post": "November 12, 2022",
        "categoryName":"Suzuki"
    },
    {
        "New Price": "25631000",
        "picture": "https://i.ibb.co/C5JR9GF/toyota-hilux.jpg",
        "name": "Suzuki Hulux",
        "company": "Suzuki",
        "location": "Chandpur",
        "Resale Price": "13031000",
        "Years": "7 years",
        "Seller":"Rashed Hossain",
        "post": "November 10, 2022",
        "categoryName":"Suzuki"
    },
    {
        "New Price": "2635000",
        "picture": "https://i.ibb.co/Nr3Tfj1/toyota-hiace.jpg",
        "name": "Suzuki Hiace",
        "company": "Suzuki",
        "location":"Dhaka, Bangladesh",
        "Resale Price": "2435000",
        "Years": "5 Years",
        "Seller":"Rasel Hossain",
        "post": "October 5, 2022",
        "categoryName":"Suzuki"
    },
    {
        "NewPrice": "20400000",
        "picture": "https://i.ibb.co/vVLdgYG/xld.jpg",
        "name": "Nissan Fortuner",
        "company": "Nissan",
        "location": "Chittagong",
        "Resale Price": "15000000",
        "Years": "5 Years",
        "Seller":"Robin Hossain",
        "post": "November 5, 2022",
        "categoryName":"Nissan"
    },
    {
        "NewPrice": "1770000",
        "picture": "https://i.ibb.co/FwGJ3p9/nissan-sunny-xldiesel.webp",
        "name": "Nissan Camre",
        "company": "Nissan",
        "location": "Savar Dhaka",
        "Resale Price": "1220000",
        "Years": "6 years",
        "Seller":"Rokib Hossain",
        "post": "October 12, 2022",
        "categoryName":"Nissan"
    },
    {
        "NewPrice": "15243000",
        "picture": "https://i.ibb.co/DYH7Mc1/nissan-magnite.webp",
        "name": "Nissan Special",
        "company": "Nissan",
        "location": "Dhanmondi, Dhaka",
        "Resale Price": "10243000",
        "Years": "2 Years",
        "Seller":"Rahul Hossain",
        "post": "October 10, 2022",
        "categoryName":"Nissan"
    },
    {
        "NewPrice": "2546000",
        "picture": "https://i.ibb.co/WtSFgFK/nissan-super-saloon.jpg",
        "name": "Nissan Vans",
        "company": "Nissan",
        "location": "Bonani Dhaka",
        "Resale Price": "2046000",
        "Years": "6 years",
        "Seller":"Robiul Hossain",
        "post": "November 12, 2022",
        "categoryName":"Nissan"
    },
    {
        "NewPrice": "25631000",
        "picture": "https://i.ibb.co/hHm6RCR/Nissan-Sunny.jpg",
        "name": "Nissan Hulux",
        "company": "Nissan",
        "location": "Chandpur",
        "Resale Price": "13031000",
        "Years": "7 years",
        "Seller":"Rashed Hossain",
        "post": "November 10, 2022",
        "categoryName":"Nissan"
    },
    {
        "NewPrice": "2635000",
        "picture": "https://i.ibb.co/g776sgG/nissan-micra.jpg",
        "name": "Nissan car",
        "company": "Nissan",
        "location":"Dhaka, Bangladesh",
        "Resale Price": "2435000",
        "Years": "5 Years",
        "Seller":"Rasel Hossain",
        "post": "October 5, 2022",
        "categoryName":"Nissan"
    },
    {
        "New Price": "20400000",
        "picture": "https://i.ibb.co/Qpn5fFR/toyota-fortuner.jpg",
        "name": "Toyota Fortuner",
        "company": "Toyota",
        "location": "Chittagong",
        "Resale Price": "15000000",
        "Years": "5 Years",
        "Seller":"Robin Hossain",
        "post": "November 5, 2022",
        "categoryName":"Toyota"
    },
    {
        "New Price": "1770000",
        "picture": "https://i.ibb.co/YDWcZcY/Toyota-Camry.jpg",
        "name": "Toyota Camre",
        "company": "Toyota",
        "location": "Savar Dhaka",
        "Resale Price": "1220000",
        "Years": "6 years",
        "Seller":"Rokib Hossain",
        "post": "October 12, 2022",
        "categoryName":"Toyota"
    },
    {
        "New Price": "15243000",
        "picture": "https://i.ibb.co/CVgW89x/toyota.jpg",
        "name": "Toyota Special",
        "company": "Toyota",
        "location": "Dhanmondi, Dhaka",
        "Resale Price": "10243000",
        "Years": "2 Years",
        "Seller":"Rahul Hossain",
        "post": "October 10, 2022",
        "categoryName":"Toyota"
    },
    {
        "New Price": "2546000",
        "picture": "https://i.ibb.co/Qr3f8mL/Toyota-vans.jpg",
        "name": "Toyota Vans",
        "company": "Toyota",
        "location": "Bonani Dhaka",
        "Resale Price": "2046000",
        "Years": "6 years",
        "Seller":"Robiul Hossain",
        "post": "November 12, 2022",
        "categoryName":"Toyota"
    },
    {
        "New Price": "25631000",
        "picture": "https://i.ibb.co/C5JR9GF/toyota-hilux.jpg",
        "name": "Toyota Hulux",
        "company": "Toyota",
        "location": "Chandpur",
        "Resale Price": "13031000",
        "Years": "7 years",
        "Seller":"Rashed Hossain",
        "post": "November 10, 2022",
        "categoryName":"Toyota"
    },
    {
        "New Price": "2635000",
        "picture": "https://i.ibb.co/Nr3Tfj1/toyota-hiace.jpg",
        "name": "Toyota Hiace",
        "company": "Toyota",
        "location":"Dhaka, Bangladesh",
        "Resale Price": "2435000",
        "Years": "5 Years",
        "Seller":"Rasel Hossain",
        "post": "October 5, 2022",
        "categoryName":"Toyota"
    }
]